birthchartSVG/__init__.py
birthchartSVG/birthchart.py
birthchartSVG/data/settings/getColors.json
birthchartSVG/data/settings/getSettingsAspect.json
birthchartSVG/data/settings/getSettingsPlanet.json
birthchartSVG/data/settings/mainSettings.json
birthchartSVG/data/template/kerykeionSVG-svg.xml
birthchartSVG/data/template/sample.svg
birthchartSVG-1.0.0.1.dist-info/METADATA
birthchartSVG-1.0.0.1.dist-info/WHEEL
birthchartSVG-1.0.0.1.dist-info/top_level.txt
birthchartSVG-1.0.0.1.dist-info/RECORD
